mermaid_component/__init__.py
mermaid_component/frontend/build/asset-manifest.json
mermaid_component/frontend/build/index.html
mermaid_component/frontend/build/precache-manifest.c9b44d581d165a5cc353a57cfa2d3ca4.js
mermaid_component/frontend/build/service-worker.js
mermaid_component/frontend/build/static/js/2.0d0a8ff5.chunk.js
mermaid_component/frontend/build/static/js/2.0d0a8ff5.chunk.js.LICENSE.txt
mermaid_component/frontend/build/static/js/2.0d0a8ff5.chunk.js.map
mermaid_component/frontend/build/static/js/main.bdfe0c11.chunk.js
mermaid_component/frontend/build/static/js/main.bdfe0c11.chunk.js.LICENSE.txt
mermaid_component/frontend/build/static/js/main.bdfe0c11.chunk.js.map
mermaid_component/frontend/build/static/js/runtime-main.71c5c8f7.js
mermaid_component/frontend/build/static/js/runtime-main.71c5c8f7.js.map
streamlit_mermaid_component-0.0.5.dist-info/LICENSE
streamlit_mermaid_component-0.0.5.dist-info/METADATA
streamlit_mermaid_component-0.0.5.dist-info/WHEEL
streamlit_mermaid_component-0.0.5.dist-info/top_level.txt
streamlit_mermaid_component-0.0.5.dist-info/RECORD
