Metadata-Version: 2.1
Name: streamlit-mermaid-component
Version: 0.0.5
Summary: A component that implements mermaid
Home-page: UNKNOWN
Author: Alexandre da Silva
Author-email: phytter@hotmail.com
License: UNKNOWN
Platform: UNKNOWN
Requires-Python: >=3.6
License-File: LICENSE
Requires-Dist: streamlit (>=0.63)
